<ref xmlns:xlink="http://www.w3.org/1999/xlink" xmlns:mml="http://www.w3.org/1998/Math/MathML" id="bb0115"><element-citation publication-type="book" id="rf0115"><person-group person-group-type="author"><name><surname>FAO</surname></name></person-group><part-title>Greater Horn of Africa and Yemen Desert Locust Crisis Appeal, January&#8211;December 2020, Rapid Response and Sustained Action (Revised Edition)</part-title><year>2020</year><publisher-name>Food and Agricultural Organisation (FAO)</publisher-name><publisher-loc>Rome</publisher-loc><ext-link ext-link-type="uri" xlink:href="http://www.fao.org/publications/card/en/c/CA9257EN/" id="ir0125">http://www.fao.org/publications/card/en/c/CA9257EN/</ext-link></element-citation></ref>