<ref xmlns:xlink="http://www.w3.org/1999/xlink" xmlns:mml="http://www.w3.org/1998/Math/MathML" id="bb0120"><element-citation publication-type="book" id="rf0120"><person-group person-group-type="author"><name><surname>FAO</surname></name><name><surname>IFAD</surname></name><name><surname>UNICEF</surname></name><name><surname>WFP</surname></name><name><surname>WHO</surname></name></person-group><part-title>The state of food security and nutrition in the world 2021</part-title><source>Transforming Food Systems for Food Security, Improved Nutrition and Affordable Healthy Diets for all</source><year>2021</year><publisher-name>FAO</publisher-name><publisher-loc>Rome</publisher-loc></element-citation></ref>