<ref xmlns:mml="http://www.w3.org/1998/Math/MathML" xmlns:xlink="http://www.w3.org/1999/xlink" id="gh2287-bib-0002"><mixed-citation publication-type="book" id="gh2287-cit-0002">
<string-name>
<surname>Anderson</surname>, <given-names>D.</given-names>
</string-name>, &amp; <string-name>
<surname>Burnham</surname>, <given-names>K.</given-names>
</string-name> (<year>2004</year>). <series>Model selection and multi&#8208;model inference</series> (<edition>2nd ed.</edition>, Vol. <volume>63</volume>(2020), 76). <publisher-name>Springer&#8208;Verlag</publisher-name>.</mixed-citation></ref>