<ref xmlns:mml="http://www.w3.org/1998/Math/MathML" xmlns:xlink="http://www.w3.org/1999/xlink" xmlns:ali="http://www.niso.org/schemas/ali/1.0/" id="CR87"><element-citation publication-type="book"><person-group person-group-type="author"><name><surname>Stuesse</surname><given-names>Angela</given-names></name></person-group><source>Scratching out a Living: Latinos, Race, and Work in the Deep South</source><year>2016</year><publisher-loc>Berkeley</publisher-loc><publisher-name>University of California Press</publisher-name></element-citation></ref>