<permissions xmlns:mml="http://www.w3.org/1998/Math/MathML" xmlns:xlink="http://www.w3.org/1999/xlink"><copyright-statement>&#169; 2022 by the authors.</copyright-statement><copyright-year>2022</copyright-year><license><ali:license_ref xmlns:ali="http://www.niso.org/schemas/ali/1.0/" specific-use="textmining" content-type="ccbylicense">https://creativecommons.org/licenses/by/4.0/</ali:license_ref><license-p>Licensee MDPI, Basel, Switzerland. This article is an open access article distributed under the terms and conditions of the Creative Commons Attribution (CC BY) license (<ext-link ext-link-type="uri" xlink:href="https://creativecommons.org/licenses/by/4.0/">https://creativecommons.org/licenses/by/4.0/</ext-link>).</license-p></license></permissions>