<ref xmlns:mml="http://www.w3.org/1998/Math/MathML" xmlns:xlink="http://www.w3.org/1999/xlink" xmlns:ali="http://www.niso.org/schemas/ali/1.0/" id="CR48"><element-citation publication-type="book"><person-group person-group-type="author"><name><surname>Klinenberg</surname><given-names>E</given-names></name></person-group><source><italic>Palaces for the people: How social infrastructure can help fight inequality, polarization, and the decline of civic life</italic></source><year>2018</year><publisher-name>Broadway Books</publisher-name></element-citation></ref>