<ref xmlns:mml="http://www.w3.org/1998/Math/MathML" xmlns:xlink="http://www.w3.org/1999/xlink" id="B18-ijerph-19-09941"><label>18.</label><element-citation publication-type="book"><person-group person-group-type="author">
<collab>United Nations</collab>
</person-group><source>Least Developed Countries Report: The Least Developed Countries in the Post-Covid World</source><publisher-name>United Nations</publisher-name><publisher-loc>San Francisco, CA, USA</publisher-loc><year>2021</year><isbn>9789211130065</isbn></element-citation></ref>