<ref xmlns:xlink="http://www.w3.org/1999/xlink" xmlns:mml="http://www.w3.org/1998/Math/MathML" id="bib2"><label>2</label><element-citation publication-type="book" id="sref2"><person-group person-group-type="author"><name><surname>Shukla</surname><given-names>P.R.</given-names></name><name><surname>Skea</surname><given-names>J.</given-names></name><name><surname>Calvo Buendia</surname><given-names>E.</given-names></name><name><surname>Masson-Delmotte</surname><given-names>V.</given-names></name><name><surname>P&#246;rtner</surname><given-names>H.-O.</given-names></name><name><surname>Roberts</surname><given-names>D.C.</given-names></name><name><surname>Zhai</surname><given-names>P.</given-names></name><name><surname>Slade</surname><given-names>R.</given-names></name><name><surname>Connors</surname><given-names>S.</given-names></name><name><surname>van Diemen</surname><given-names>R.</given-names></name></person-group><chapter-title>Climate change and land: an IPCC special report on climate change, desertification, land degradation, sustainable land management, food security, and greenhouse gas fluxes in terrestrial ecosystems</chapter-title><year>2019</year><publisher-name>Intergovernmental Panel on&#160;Climate Change</publisher-name><ext-link ext-link-type="uri" xlink:href="https://www.ipcc.ch/site/assets/uploads/sites/4/2020/02/SRCCL-Complete-BOOK-LRES.pdf" id="intref0015">https://www.ipcc.ch/site/assets/uploads/sites/4/2020/02/SRCCL-Complete-BOOK-LRES.pdf</ext-link></element-citation></ref>