{"downloaded": true, "htmlmade": false, "id": "36180440", "source": "MED", "pmid": "36180440", "pmcid": "PMC9524340", "fullTextIdList": {"fullTextId": "PMC9524340"}, "doi": "10.1038/s41467-022-33392-9", "title": "US cities increasingly integrate justice into climate planning and create policy tools for climate justice.", "authorString": "Diezmart\u00ednez CV, Short Gianotti AG.", "authorList": {"author": [{"fullName": "Diezmart\u00ednez CV", "firstName": "Claudia V", "lastName": "Diezmart\u00ednez", "initials": "CV", "authorId": {"@type": "ORCID", "#text": "0000-0002-2340-4628"}, "authorAffiliationDetailsList": {"authorAffiliation": {"affiliation": "Department of Earth and Environment, Boston University, Boston, MA, USA. cvdiezm@bu.edu."}}}, {"fullName": "Short Gianotti AG", "firstName": "Anne G", "lastName": "Short Gianotti", "initials": "AG", "authorAffiliationDetailsList": {"authorAffiliation": {"affiliation": "Department of Earth and Environment, Boston University, Boston, MA, USA."}}}]}, "authorIdList": {"authorId": {"@type": "ORCID", "#text": "0000-0002-2340-4628"}}, "dataLinksTagsList": {"dataLinkstag": "altmetrics"}, "journalInfo": {"issue": "1", "volume": "13", "journalIssueId": "3415938", "dateOfPublication": "2022 Sep", "monthOfPublication": "9", "yearOfPublication": "2022", "printPublicationDate": "2022-09-01", "journal": {"title": "Nature communications", "ISOAbbreviation": "Nat Commun", "medlineAbbreviation": "Nat Commun", "NLMid": "101528555", "ISSN": "2041-1723", "ESSN": "2041-1723"}}, "pubYear": "2022", "pageInfo": "5763", "abstractText": "Climate change is one of the most important ethical issues of our time. Urban scholars and policymakers now recognise the need to address justice concerns associated with cities' responses to climate change. However, little empirical research has examined whether and how cities have integrated justice into climate mitigation planning. Here, we show that large cities in the US are increasingly attending to justice in their climate action plans and that the recognition of structural and historical injustices is becoming more common. We demonstrate that justice is articulated differently across mitigation sectors, uncover local characteristics that may impact cities' level of engagement with justice, and introduce four policy tools that pioneer cities have developed to operationalise just climate policies on the ground. More attention to justice in policy implementation and evaluation is needed as cities continue to move toward just urban transitions.", "affiliation": "Department of Earth and Environment, Boston University, Boston, MA, USA. cvdiezm@bu.edu.", "publicationStatus": "epublish", "language": "eng", "pubModel": "Electronic", "pubTypeList": {"pubType": ["research-article", "Journal Article"]}, "grantsList": {"grant": {"agency": "Boston University", "orderIn": "0"}}, "meshHeadingList": {"meshHeading": [{"majorTopic_YN": "N", "descriptorName": "Cities"}, {"majorTopic_YN": "Y", "descriptorName": "Social Justice"}, {"majorTopic_YN": "Y", "descriptorName": "Climate Change"}, {"majorTopic_YN": "N", "descriptorName": "Policy"}]}, "subsetList": {"subset": {"code": "IM", "name": "Index Medicus"}}, "fullTextUrlList": {"fullTextUrl": [{"availability": "Subscription required", "availabilityCode": "S", "documentStyle": "doi", "site": "DOI", "url": "https://doi.org/10.1038/s41467-022-33392-9"}, {"availability": "Open access", "availabilityCode": "OA", "documentStyle": "html", "site": "Europe_PMC", "url": "https://europepmc.org/articles/PMC9524340"}, {"availability": "Open access", "availabilityCode": "OA", "documentStyle": "pdf", "site": "Europe_PMC", "url": "https://europepmc.org/articles/PMC9524340?pdf=render"}]}, "isOpenAccess": "Y", "inEPMC": "Y", "inPMC": "N", "hasPDF": "Y", "hasBook": "N", "hasSuppl": "Y", "citedByCount": "0", "hasData": "Y", "hasReferences": "Y", "hasTextMinedTerms": "Y", "hasDbCrossReferences": "N", "hasLabsLinks": "Y", "license": "cc by", "authMan": "N", "epmcAuthMan": "N", "nihAuthMan": "N", "hasTMAccessionNumbers": "N", "dateOfCompletion": "2022-10-04", "dateOfCreation": "2022-09-30", "firstIndexDate": "2022-10-02", "fullTextReceivedDate": "2022-10-04", "dateOfRevision": "2022-10-04", "electronicPublicationDate": "2022-09-30", "firstPublicationDate": "2022-09-30"}