<ref xmlns:mml="http://www.w3.org/1998/Math/MathML" xmlns:xlink="http://www.w3.org/1999/xlink" id="B25"><mixed-citation publication-type="book"><person-group person-group-type="author"><name><surname>Lacy</surname><given-names>P.</given-names></name><name><surname>Keeble</surname><given-names>J.</given-names></name><name><surname>McNamara</surname><given-names>R.</given-names></name><name><surname>Rutqvist</surname><given-names>J.</given-names></name><name><surname>Haglund</surname><given-names>T.</given-names></name></person-group> (<year>2014</year>). <source>Circular Advantage: Innovative Business Models and Technologies to Create Value in a World Without Limits to Growth.</source>
<publisher-loc>Chicago, IL</publisher-loc>: <publisher-name>Accenture</publisher-name>.</mixed-citation></ref>